gnocchi/__init__.py
gnocchi/amqp1d.py
gnocchi/archive_policy.py
gnocchi/calendar.py
gnocchi/carbonara.py
gnocchi/chef.py
gnocchi/exceptions.py
gnocchi/gendoc.py
gnocchi/gnocchi-config-generator.conf
gnocchi/gnocchi-policy-generator.conf
gnocchi/json.py
gnocchi/opts.py
gnocchi/resource_type.py
gnocchi/service.py
gnocchi/statsd.py
gnocchi/utils.py
gnocchi/cli/__init__.py
gnocchi/cli/amqp1d.py
gnocchi/cli/api.py
gnocchi/cli/injector.py
gnocchi/cli/manage.py
gnocchi/cli/metricd.py
gnocchi/cli/statsd.py
gnocchi/common/__init__.py
gnocchi/common/ceph.py
gnocchi/common/redis.py
gnocchi/common/s3.py
gnocchi/common/swift.py
gnocchi/incoming/__init__.py
gnocchi/incoming/ceph.py
gnocchi/incoming/file.py
gnocchi/incoming/redis.py
gnocchi/incoming/s3.py
gnocchi/incoming/swift.py
gnocchi/indexer/__init__.py
gnocchi/indexer/sqlalchemy.py
gnocchi/indexer/sqlalchemy_base.py
gnocchi/indexer/sqlalchemy_extension.py
gnocchi/indexer/sqlalchemy_legacy_resources.py
gnocchi/indexer/sqlalchemy_types.py
gnocchi/indexer/alembic/alembic.ini
gnocchi/indexer/alembic/env.py
gnocchi/indexer/alembic/script.py.mako
gnocchi/indexer/alembic/versions/04eba72e4f90_rename_ck_started_before_ended.py
gnocchi/indexer/alembic/versions/0718ed97e5b3_add_tablename_to_resource_type.py
gnocchi/indexer/alembic/versions/18fff4509e3e_create_column_for_truncate_inactive_metrics_process.py
gnocchi/indexer/alembic/versions/1c2c61ac1f4c_add_original_resource_id_column.py
gnocchi/indexer/alembic/versions/1c98ac614015_initial_base.py
gnocchi/indexer/alembic/versions/1e1a63d3d186_original_resource_id_not_null.py
gnocchi/indexer/alembic/versions/1f21cbdd6bc2_allow_volume_display_name_to_be_null.py
gnocchi/indexer/alembic/versions/27d2a1d205ff_add_updating_resource_type_states.py
gnocchi/indexer/alembic/versions/2e0b912062d1_drop_useless_enum.py
gnocchi/indexer/alembic/versions/34c517bcc2dd_shorter_foreign_key.py
gnocchi/indexer/alembic/versions/3901f5ea2b8e_create_instance_disk_and_instance_.py
gnocchi-4.7.0.dist-info/licenses/LICENSE
gnocchi-4.7.0.dist-info/METADATA
gnocchi-4.7.0.dist-info/WHEEL
gnocchi-4.7.0.dist-info/entry_points.txt
gnocchi-4.7.0.dist-info/top_level.txt
gnocchi-4.7.0.dist-info/RECORD
