Metadata-Version: 2.4
Name: gnocchi
Version: 4.7.0
Summary: Metric as a Service
Home-page: http://gnocchi.osci.io
Author: Gnocchi developers
Classifier: Intended Audience :: Information Technology
Classifier: Intended Audience :: System Administrators
Classifier: License :: OSI Approved :: Apache Software License
Classifier: Operating System :: POSIX :: Linux
Classifier: Programming Language :: Python
Classifier: Programming Language :: Python :: 3
Classifier: Programming Language :: Python :: 3 :: Only
Classifier: Programming Language :: Python :: 3.9
Classifier: Programming Language :: Python :: 3.10
Classifier: Programming Language :: Python :: 3.11
Classifier: Programming Language :: Python :: 3.12
Classifier: Topic :: System :: Monitoring
License-File: LICENSE
Requires-Dist: numpy>=1.14.0
Requires-Dist: iso8601
Requires-Dist: oslo.config>=3.22.0
Requires-Dist: oslo.policy>=4.5.0
Requires-Dist: oslo.middleware>=3.22.0
Requires-Dist: oslo.utils>=1.1.1
Requires-Dist: pytimeparse
Requires-Dist: pecan>=0.9
Requires-Dist: jsonpatch
Requires-Dist: cotyledon>=1.5.0
Requires-Dist: stevedore
Requires-Dist: ujson
Requires-Dist: voluptuous>=0.8.10
Requires-Dist: werkzeug
Requires-Dist: tenacity>=5.0.0
Requires-Dist: WebOb>=1.4.1
Requires-Dist: Paste
Requires-Dist: PasteDeploy
Requires-Dist: daiquiri
Requires-Dist: pyparsing>=2.2.0
Requires-Dist: lz4>=0.9.0
Requires-Dist: tooz>=1.38
Requires-Dist: cachetools
Requires-Dist: importlib_metadata>=3.6; python_version < "3.10"
Provides-Extra: keystone
Requires-Dist: keystonemiddleware!=4.19.0,>=4.0.0; extra == "keystone"
Provides-Extra: mysql
Requires-Dist: pymysql; extra == "mysql"
Requires-Dist: oslo.db>=4.29.0; extra == "mysql"
Requires-Dist: sqlalchemy>=1.4.24; extra == "mysql"
Requires-Dist: sqlalchemy-utils; extra == "mysql"
Requires-Dist: alembic!=0.8.1,!=0.9.0,>=0.7.6; extra == "mysql"
Provides-Extra: postgresql
Requires-Dist: psycopg2; extra == "postgresql"
Requires-Dist: oslo.db>=4.29.0; extra == "postgresql"
Requires-Dist: sqlalchemy>=1.4.24; extra == "postgresql"
Requires-Dist: sqlalchemy-utils; extra == "postgresql"
Requires-Dist: alembic!=0.8.1,!=0.9.0,>=0.7.6; extra == "postgresql"
Provides-Extra: s3
Requires-Dist: boto3; extra == "s3"
Requires-Dist: botocore>=1.5; extra == "s3"
Provides-Extra: redis
Requires-Dist: redis>=3.4.0; extra == "redis"
Requires-Dist: hiredis; extra == "redis"
Provides-Extra: swift
Requires-Dist: python-swiftclient>=3.1.0; extra == "swift"
Provides-Extra: ceph
Provides-Extra: ceph-alternative
Requires-Dist: python-rados>=12.2.0; extra == "ceph-alternative"
Provides-Extra: prometheus
Requires-Dist: python-snappy; extra == "prometheus"
Requires-Dist: protobuf>=3.19.0; extra == "prometheus"
Provides-Extra: amqp1
Requires-Dist: python-qpid-proton>=0.17.0; extra == "amqp1"
Provides-Extra: doc
Requires-Dist: sphinx; extra == "doc"
Requires-Dist: furo; extra == "doc"
Requires-Dist: sphinxcontrib-httpdomain; extra == "doc"
Requires-Dist: PyYAML; extra == "doc"
Requires-Dist: Jinja2; extra == "doc"
Requires-Dist: reno>=1.6.2; extra == "doc"
Provides-Extra: test
Requires-Dist: pifpaf[gnocchi]; extra == "test"
Requires-Dist: gabbi<4,>=1.37.0; extra == "test"
Requires-Dist: coverage>=3.6; extra == "test"
Requires-Dist: fixtures; extra == "test"
Requires-Dist: python-subunit>=0.0.18; extra == "test"
Requires-Dist: stestr>=2.0.0; extra == "test"
Requires-Dist: testscenarios; extra == "test"
Requires-Dist: testresources>=0.2.4; extra == "test"
Requires-Dist: testtools>=0.9.38; extra == "test"
Requires-Dist: WebTest>=3.0; extra == "test"
Requires-Dist: keystonemiddleware!=4.19.0,>=4.0.0; extra == "test"
Requires-Dist: wsgi_intercept>=1.4.1; extra == "test"
Requires-Dist: xattr!=0.9.4; extra == "test"
Provides-Extra: test-swift
Requires-Dist: python-swiftclient; extra == "test-swift"
Dynamic: license-file
